{"nodes": [{"id": "c_projects_all_in_one_lib_services_theme_service_dart", "label": "theme_service.dart", "file_type": "code", "source_file": "C:\\Projects\\all in one\\lib\\services\\theme_service.dart", "source_location": null}, {"id": "c_projects_all_in_one_lib_services_theme_service_dart_appbrandgradients", "label": "AppBrandGradients", "file_type": "code", "source_file": "C:\\Projects\\all in one\\lib\\services\\theme_service.dart", "source_location": null}, {"id": "c_projects_all_in_one_lib_services_theme_service_dart_appbrandtheme", "label": "AppBrandTheme", "file_type": "code", "source_file": "C:\\Projects\\all in one\\lib\\services\\theme_service.dart", "source_location": null}, {"id": "c_projects_all_in_one_lib_services_theme_service_dart_purpletheme", "label": "PurpleTheme", "file_type": "code", "source_file": "C:\\Projects\\all in one\\lib\\services\\theme_service.dart", "source_location": null}, {"id": "c_projects_all_in_one_lib_services_theme_service_dart_originalpurpletheme", "label": "OriginalPurpleTheme", "file_type": "code", "source_file": "C:\\Projects\\all in one\\lib\\services\\theme_service.dart", "source_location": null}, {"id": "c_projects_all_in_one_lib_services_theme_service_dart_njpinkwhitetheme", "label": "NJPinkWhiteTheme", "file_type": "code", "source_file": "C:\\Projects\\all in one\\lib\\services\\theme_service.dart", "source_location": null}, {"id": "c_projects_all_in_one_lib_services_theme_service_dart_themeservice", "label": "ThemeService", "file_type": "code", "source_file": "C:\\Projects\\all in one\\lib\\services\\theme_service.dart", "source_location": null}, {"id": "c_projects_all_in_one_lib_services_theme_service_dart_copywith", "label": "copyWith", "file_type": "code", "source_file": "C:\\Projects\\all in one\\lib\\services\\theme_service.dart", "source_location": null}, {"id": "c_projects_all_in_one_lib_services_theme_service_dart_lerp", "label": "lerp", "file_type": "code", "source_file": "C:\\Projects\\all in one\\lib\\services\\theme_service.dart", "source_location": null}, {"id": "c_projects_all_in_one_lib_services_theme_service_dart_light", "label": "light", "file_type": "code", "source_file": "C:\\Projects\\all in one\\lib\\services\\theme_service.dart", "source_location": null}, {"id": "c_projects_all_in_one_lib_services_theme_service_dart_themedata", "label": "ThemeData", "file_type": "code", "source_file": "C:\\Projects\\all in one\\lib\\services\\theme_service.dart", "source_location": null}, {"id": "dart_async", "label": "dart:async", "file_type": "code", "source_file": "C:\\Projects\\all in one\\lib\\services\\theme_service.dart", "source_location": null}, {"id": "package_flutter_material_dart", "label": "package:flutter/material.dart", "file_type": "code", "source_file": "C:\\Projects\\all in one\\lib\\services\\theme_service.dart", "source_location": null}, {"id": "package_google_fonts_google_fonts_dart", "label": "package:google_fonts/google_fonts.dart", "file_type": "code", "source_file": "C:\\Projects\\all in one\\lib\\services\\theme_service.dart", "source_location": null}, {"id": "package_shared_preferences_shared_preferences_dart", "label": "package:shared_preferences/shared_preferences.dart", "file_type": "code", "source_file": "C:\\Projects\\all in one\\lib\\services\\theme_service.dart", "source_location": null}], "edges": [{"source": "c_projects_all_in_one_lib_services_theme_service_dart", "target": "c_projects_all_in_one_lib_services_theme_service_dart_appbrandgradients", "relation": "defines", "confidence": "EXTRACTED", "confidence_score": 1.0, "source_file": "C:\\Projects\\all in one\\lib\\services\\theme_service.dart", "source_location": null, "weight": 1.0}, {"source": "c_projects_all_in_one_lib_services_theme_service_dart", "target": "c_projects_all_in_one_lib_services_theme_service_dart_appbrandtheme", "relation": "defines", "confidence": "EXTRACTED", "confidence_score": 1.0, "source_file": "C:\\Projects\\all in one\\lib\\services\\theme_service.dart", "source_location": null, "weight": 1.0}, {"source": "c_projects_all_in_one_lib_services_theme_service_dart", "target": "c_projects_all_in_one_lib_services_theme_service_dart_purpletheme", "relation": "defines", "confidence": "EXTRACTED", "confidence_score": 1.0, "source_file": "C:\\Projects\\all in one\\lib\\services\\theme_service.dart", "source_location": null, "weight": 1.0}, {"source": "c_projects_all_in_one_lib_services_theme_service_dart", "target": "c_projects_all_in_one_lib_services_theme_service_dart_originalpurpletheme", "relation": "defines", "confidence": "EXTRACTED", "confidence_score": 1.0, "source_file": "C:\\Projects\\all in one\\lib\\services\\theme_service.dart", "source_location": null, "weight": 1.0}, {"source": "c_projects_all_in_one_lib_services_theme_service_dart", "target": "c_projects_all_in_one_lib_services_theme_service_dart_njpinkwhitetheme", "relation": "defines", "confidence": "EXTRACTED", "confidence_score": 1.0, "source_file": "C:\\Projects\\all in one\\lib\\services\\theme_service.dart", "source_location": null, "weight": 1.0}, {"source": "c_projects_all_in_one_lib_services_theme_service_dart", "target": "c_projects_all_in_one_lib_services_theme_service_dart_themeservice", "relation": "defines", "confidence": "EXTRACTED", "confidence_score": 1.0, "source_file": "C:\\Projects\\all in one\\lib\\services\\theme_service.dart", "source_location": null, "weight": 1.0}, {"source": "c_projects_all_in_one_lib_services_theme_service_dart", "target": "c_projects_all_in_one_lib_services_theme_service_dart_copywith", "relation": "defines", "confidence": "EXTRACTED", "confidence_score": 1.0, "source_file": "C:\\Projects\\all in one\\lib\\services\\theme_service.dart", "source_location": null, "weight": 1.0}, {"source": "c_projects_all_in_one_lib_services_theme_service_dart", "target": "c_projects_all_in_one_lib_services_theme_service_dart_lerp", "relation": "defines", "confidence": "EXTRACTED", "confidence_score": 1.0, "source_file": "C:\\Projects\\all in one\\lib\\services\\theme_service.dart", "source_location": null, "weight": 1.0}, {"source": "c_projects_all_in_one_lib_services_theme_service_dart", "target": "c_projects_all_in_one_lib_services_theme_service_dart_light", "relation": "defines", "confidence": "EXTRACTED", "confidence_score": 1.0, "source_file": "C:\\Projects\\all in one\\lib\\services\\theme_service.dart", "source_location": null, "weight": 1.0}, {"source": "c_projects_all_in_one_lib_services_theme_service_dart", "target": "c_projects_all_in_one_lib_services_theme_service_dart_themedata", "relation": "defines", "confidence": "EXTRACTED", "confidence_score": 1.0, "source_file": "C:\\Projects\\all in one\\lib\\services\\theme_service.dart", "source_location": null, "weight": 1.0}, {"source": "c_projects_all_in_one_lib_services_theme_service_dart", "target": "dart_async", "relation": "imports", "confidence": "EXTRACTED", "confidence_score": 1.0, "source_file": "C:\\Projects\\all in one\\lib\\services\\theme_service.dart", "source_location": null, "weight": 1.0}, {"source": "c_projects_all_in_one_lib_services_theme_service_dart", "target": "package_flutter_material_dart", "relation": "imports", "confidence": "EXTRACTED", "confidence_score": 1.0, "source_file": "C:\\Projects\\all in one\\lib\\services\\theme_service.dart", "source_location": null, "weight": 1.0}, {"source": "c_projects_all_in_one_lib_services_theme_service_dart", "target": "package_google_fonts_google_fonts_dart", "relation": "imports", "confidence": "EXTRACTED", "confidence_score": 1.0, "source_file": "C:\\Projects\\all in one\\lib\\services\\theme_service.dart", "source_location": null, "weight": 1.0}, {"source": "c_projects_all_in_one_lib_services_theme_service_dart", "target": "package_shared_preferences_shared_preferences_dart", "relation": "imports", "confidence": "EXTRACTED", "confidence_score": 1.0, "source_file": "C:\\Projects\\all in one\\lib\\services\\theme_service.dart", "source_location": null, "weight": 1.0}]}